snaccel/__init__.py
snaccel-0.1.0.dist-info/METADATA
snaccel-0.1.0.dist-info/WHEEL
snaccel-0.1.0.dist-info/top_level.txt
snaccel-0.1.0.dist-info/RECORD
